image2image/__init__.py
image2image/__main__.py
image2image/__main_elastix__.py
image2image/__main_register__.py
image2image/__main_viewer__.py
image2image/cli.py
image2image/config.py
image2image/constants.py
image2image/enums.py
image2image/exceptions.py
image2image/main.py
image2image/py.typed
image2image/assets/__init__.py
image2image/assets/icon.icns
image2image/assets/icon.ico
image2image/assets/icon.png
image2image/assets/icon.svg
image2image/assets/stylesheets/10_custom.qss
image2image/models/__init__.py
image2image/models/base.py
image2image/models/data.py
image2image/models/misc.py
image2image/models/transform.py
image2image/models/transformation.py
image2image/models/utilities.py
image2image/models/wsiprep.py
image2image/qt/__init__.py
image2image/qt/_dialog_base.py
image2image/qt/_dialog_mixins.py
image2image/qt/_dialog_wsi.py
image2image/qt/dialog_convert.py
image2image/qt/dialog_crop.py
image2image/qt/dialog_elastix.py
image2image/qt/dialog_elastix3d.py
image2image/qt/dialog_fusion.py
image2image/qt/dialog_merge.py
image2image/qt/dialog_register.py
image2image/qt/dialog_valis.py
image2image/qt/dialog_viewer.py
image2image/qt/event_loop.py
image2image/qt/launcher.py
image2image/qt/_dialogs/__init__.py
image2image/qt/_dialogs/_about.py
image2image/qt/_dialogs/_dataset.py
image2image/qt/_dialogs/_errors.py
image2image/qt/_dialogs/_extract.py
image2image/qt/_dialogs/_iterate.py
image2image/qt/_dialogs/_list.py
image2image/qt/_dialogs/_locate.py
image2image/qt/_dialogs/_rename.py
image2image/qt/_dialogs/_save.py
image2image/qt/_dialogs/_scalebar.py
image2image/qt/_dialogs/_select.py
image2image/qt/_dialogs/_sentry.py
image2image/qt/_dialogs/_shortcuts.py
image2image/qt/_dialogs/_sysinfo.py
image2image/qt/_dialogs/_tutorial.py
image2image/qt/_dialogs/_update.py
image2image/qt/_register/__init__.py
image2image/qt/_register/_fiducials.py
image2image/qt/_register/_guess.py
image2image/qt/_register/_preprocess.py
image2image/qt/_register/_select.py
image2image-0.2.3.dist-info/METADATA
image2image-0.2.3.dist-info/WHEEL
image2image-0.2.3.dist-info/entry_points.txt
image2image-0.2.3.dist-info/licenses/LICENSE
image2image-0.2.3.dist-info/RECORD
