Metadata-Version: 2.4
Name: image2image
Version: 0.2.3
Summary: Image visualization and registration app.
Project-URL: homepage, https://github.com/vandeplaslab/image2image
Project-URL: repository, https://github.com/vandeplaslab/image2image
Author-email: "Lukasz G. Migas" <lukas.migas@yahoo.com>
License: BSD 3-Clause License
License-File: LICENSE
Classifier: Development Status :: 3 - Alpha
Classifier: Environment :: X11 Applications :: Qt
Classifier: Intended Audience :: Education
Classifier: Intended Audience :: Science/Research
Classifier: License :: OSI Approved :: BSD License
Classifier: Natural Language :: English
Classifier: Operating System :: MacOS
Classifier: Operating System :: Microsoft :: Windows
Classifier: Operating System :: POSIX
Classifier: Operating System :: Unix
Classifier: Programming Language :: Python :: 3
Classifier: Programming Language :: Python :: 3.10
Classifier: Programming Language :: Python :: 3.11
Classifier: Programming Language :: Python :: 3.12
Classifier: Programming Language :: Python :: 3.13
Classifier: Topic :: Scientific/Engineering
Classifier: Topic :: Scientific/Engineering :: Bio-Informatics
Classifier: Topic :: Scientific/Engineering :: Information Analysis
Classifier: Topic :: Scientific/Engineering :: Visualization
Classifier: Topic :: Utilities
Classifier: Typing :: Typed
Requires-Python: >=3.10
Requires-Dist: glasbey
Requires-Dist: image2image-io>=0.2.3
Requires-Dist: image2image-reg>=0.2.3
Requires-Dist: lxml==4.9.2; python_version < '3.12'
Requires-Dist: lxml==5.4.0; python_version >= '3.12'
Requires-Dist: numba; python_version >= '3.13'
Requires-Dist: numba<0.60; python_version < '3.13'
Requires-Dist: numpy
Requires-Dist: pandas<2; python_version < '3.13'
Requires-Dist: pandas>=2; python_version >= '3.13'
Requires-Dist: pydantic>=2
Requires-Dist: qtextra[console,sentry]>=0.1.7
Requires-Dist: qtextraplot[2d,mpl]>=0.1.1
Requires-Dist: qtpy
Requires-Dist: rasterio
Requires-Dist: toml
Requires-Dist: xarray<=2024.3.0
Provides-Extra: dev
Requires-Dist: ipython; extra == 'dev'
Requires-Dist: mypy; extra == 'dev'
Requires-Dist: pdbpp; extra == 'dev'
Requires-Dist: pre-commit; extra == 'dev'
Requires-Dist: pytest-cov>=6.1.1; extra == 'dev'
Requires-Dist: pytest-qt; extra == 'dev'
Requires-Dist: pytest>=8.3.5; extra == 'dev'
Requires-Dist: qtreload; extra == 'dev'
Requires-Dist: rich; extra == 'dev'
Requires-Dist: ruff; extra == 'dev'
Provides-Extra: pyqt5
Requires-Dist: pyqt5; extra == 'pyqt5'
Provides-Extra: pyqt6
Requires-Dist: pyqt6; extra == 'pyqt6'
Provides-Extra: pyside2
Requires-Dist: pyside2; extra == 'pyside2'
Provides-Extra: pyside6
Requires-Dist: pyside6; extra == 'pyside6'
Provides-Extra: test
Requires-Dist: pytest-cov>=6.1.1; extra == 'test'
Requires-Dist: pytest-qt; extra == 'test'
Requires-Dist: pytest>=8.3.5; extra == 'test'
